nextcloud_micos_export-0.5.6.dist-info/METADATA
nextcloud_micos_export-0.5.6.dist-info/WHEEL
nextcloud_micos_export-0.5.6.dist-info/entry_points.txt
nextcloud_micos_export/__init__.py
nextcloud_micos_export/__main__.py
nextcloud_micos_export/file_name_models.py
nextcloud_micos_export/settings.py
nextcloud_micos_export-0.5.6.dist-info/RECORD
