Metadata-Version: 2.1
Name: nextcloud-micos-export
Version: 0.5.6
Summary: Move files from input to output folder and delete old files from output folder.
Author-Email: "Kirchhoff Datensysteme Services GmbH & Co. KG" <service@kds-kg.de>
License: GPL-3.0
Requires-Python: >=3.11
Requires-Dist: wiederverwendbar[rich]>=0.7.2
Requires-Dist: pid>=3.0.4
Requires-Dist: PyMySQL>=1.1.1
Requires-Dist: schedule>=1.2.2
